onCall.py
keep_tools_oncall-1.0.2.dist-info/LICENSE
keep_tools_oncall-1.0.2.dist-info/METADATA
keep_tools_oncall-1.0.2.dist-info/WHEEL
keep_tools_oncall-1.0.2.dist-info/entry_points.txt
keep_tools_oncall-1.0.2.dist-info/top_level.txt
keep_tools_oncall-1.0.2.dist-info/RECORD
